AXI/FIFO.v
module FIFO #(
    parameter d_width = 101
)
(
    input clk, rst_n,
    input i_push, i_pop,
    input [d_width -1 : 0] i_data,

    output o_empty,
    output o_full,
    output [d_width -1 : 0] o_data
);

reg [3:0] w_ptr, r_ptr;
reg [d_width -1 : 0] mem_data [0:15];
integer i;
always @(posedge clk or negedge rst_n) begin
    if(!rst_n) begin
        for(i = 0; i < 16; i = i + 1) begin
            mem_data[i] <= 101'd0;
        end
        w_ptr <= 0;
        r_ptr <= 0;
    end
    else begin
        if(i_push && !o_full) begin
            mem_data[w_ptr] <= i_data;
            w_ptr <= w_ptr + 1;
        end
        if(i_pop && !o_empty) begin
            r_ptr <= r_ptr + 1;
        end
    end
end

assign o_data = mem_data[r_ptr];
assign o_full = ((w_ptr + 1) == r_ptr) ? 1 : 0;
assign o_empty = (w_ptr == r_ptr) ? 1 : 0;

endmodule

TILELINK/RAM.v
module RAM(
    input clk, rst_n,

    input i_wen,
    input [31:0] i_write_address,
    input [63:0] i_data,

    input i_ren,
    input [31:0] i_read_address,
    output reg [63:0] o_data
);

reg [7:0] mem_data [0:1023];
integer i;
initial begin
    for(i = 0; i < 1024; i = i + 1) begin
        mem_data[i] = 8'd0;
    end
end

always @(posedge clk) begin
    if(i_wen) begin
        mem_data[i_write_address] <= i_data[7:0];
        mem_data[i_write_address + 1] <= i_data[15:8];
        mem_data[i_write_address + 2] <= i_data[23:16];
        mem_data[i_write_address + 3] <= i_data[31:24];
        mem_data[i_write_address + 4] <= i_data[39:32];
        mem_data[i_write_address + 5] <= i_data[47:40];
        mem_data[i_write_address + 6] <= i_data[55:48];
        mem_data[i_write_address + 7] <= i_data[63:56];
    end
end

always @(posedge clk) begin
    o_data <= 64'd0;
    if(i_ren) begin
        o_data[7:0] <= mem_data[i_read_address];
        o_data[15:8] <= mem_data[i_read_address + 1];
        o_data[23:16] <= mem_data[i_read_address + 2];
        o_data[31:24] <= mem_data[i_read_address + 3];
        o_data[39:32] <= mem_data[i_read_address + 4];
        o_data[47:40] <= mem_data[i_read_address + 5];
        o_data[55:48] <= mem_data[i_read_address + 6];
        o_data[63:56] <= mem_data[i_read_address + 7];
    end
end


endmodule

TILELINK/FSM_d_masterv1.v
module FSM_d_masterv1 #(
    parameter band_width = 3
)
(
    input clk, rst_n,
    input i_empty_FIFO_request,
    output reg o_pop_FIFO_request,
    input [36:0] i_read_request,

    output reg o_ren,
    output reg [31:0] o_read_address,

    input s_d_ready,
    output reg s_d_valid,
    output reg [36:0] o_header
);

localparam IDLE = 0,
           READ_BURST = 1;
reg state, next_state;


reg [36:0] reg_read_request;
always @(posedge clk or negedge rst_n) begin
    if(!rst_n) begin
        reg_read_request <= 0;
        o_pop_FIFO_request <= 1'b0;
    end
    else begin
        if(i_empty_FIFO_request && state == IDLE) begin
            reg_read_request <= i_read_request;
            o_pop_FIFO_request <= 1'b1;
        end
        else begin
//            reg_read_request <= 0;
            o_pop_FIFO_request <= 1'b0;
        end
    end
end

wire [2:0] opcode;
wire [2:0] size;
wire [3:0] mark;
wire [26:0] address;
assign opcode = reg_read_request[36:34];
assign size = reg_read_request[33:31];
assign mark = reg_read_request[30:27];
assign address = reg_read_request[26:0];

wire [3:0] beat;
wire [3:0] cnt_read_burst;
assign beat = ({1'b0, size}) - ({1'b0, band_width});
assign cnt_read_burst = (beat >= 0) ? ((1 << beat)) : 1;
reg [3:0] cnt;


always @(*) begin
    case(state)
        IDLE: next_state = (i_empty_FIFO_request) ? READ_BURST : IDLE;
        READ_BURST: next_state = (opcode == 0 || cnt == cnt_read_burst) ? IDLE : READ_BURST;
    endcase
end

always @(posedge clk or negedge rst_n) begin
    if(!rst_n) begin
        state <= IDLE;
    end
    else begin
        state <= next_state;
    end
end


reg [5:0] offset;
always @(posedge clk or negedge rst_n) begin
    if(!rst_n) begin
        cnt <= 0;
    end
    else begin
        if(state == READ_BURST && opcode == 1 && s_d_ready && cnt != cnt_read_burst) begin
            cnt <= cnt + 1;
        end
        else if(cnt == cnt_read_burst || state == IDLE) begin
            cnt <= 0;
        end
    end
end
always @(*) begin
    offset = cnt << 3;
end

always @(*) begin
    if(state == READ_BURST && opcode == 1 && cnt != cnt_read_burst && s_d_ready) begin
        o_ren <= 1'b1;
        o_read_address <= {address, offset};
    end
    else begin
        o_ren <= 1'b0;
        o_read_address <= 32'd0; 
    end
end


always @(posedge clk or negedge rst_n) begin
    if(!rst_n) begin
        s_d_valid <= 0;
    end
    else begin
        if((state == READ_BURST) && s_d_ready && cnt != cnt_read_burst) begin
            s_d_valid <= 1;
        end
        else begin
            s_d_valid <= 0;
        end
    end
end

always @(posedge clk or negedge rst_n) begin
    if(!rst_n) begin
        o_header <= 0;
    end
    else begin
        if((opcode == 0 || opcode == 1) && s_d_ready ) begin
            o_header =  {opcode, size, mark, address};
        end
    end
end


endmodule

TILELINK/FSM_a_slavev1.v
module FSM_a_slavev1 #(
    parameter [2:0] band_width = 3
)
(
    input clk, rst_n,

    input m_a_valid,
    output reg m_a_ready,

    input [100:0] i_header,
    output reg o_wen,
    output reg [95:0] o_packet, // address = 32, data = 64;

    output reg [36:0] o_read_request,
    output reg o_push_request,
    input i_full_FIFO_request
);

wire [2:0] opcode;
wire [2:0] size;
wire [3:0] mark; 
wire [26:0] address;
wire [63:0] data;
assign opcode = i_header[100:98];
assign size = i_header[97:95];
assign mark = i_header[94:91];
assign address = i_header[90:64];
assign data = i_header[63:0];

wire [3:0] beat;
wire [3:0] cnt_push_burst;
assign beat = ({1'b0, size}) - ({1'b0, band_width});
assign cnt_push_burst = (beat >= 0) ? ((1 << beat)) : 3'd1;
reg [3:0] cnt;
reg [5:0] offset;



always @(posedge clk or negedge rst_n) begin
    if(!rst_n) begin
        cnt <= 1;
    end
    else begin
        if(m_a_valid) begin
            cnt <= cnt + 1;
            if(cnt == cnt_push_burst) begin
                cnt <= 0;
            end
        end
    end
end

always @(*) begin
    offset = (cnt - 1) << 3;
end

always @(*) begin
    m_a_ready = 0;
    if(m_a_valid) begin
        m_a_ready = 1;
    end
end

always @(*) begin
    o_wen = 1'b0;
    o_packet = 96'd0;
    if(m_a_valid && opcode == 0) begin
        o_wen = 1'b1;
        o_packet = {address, offset, data};
    end
end


always @(posedge clk or negedge rst_n) begin
    if(!rst_n) begin
        o_read_request <= 37'd0;
        o_push_request <= 0;
    end
    else begin
        if(opcode == 4 && i_full_FIFO_request) begin
            o_read_request <= {3'b001, size, mark, address};
            o_push_request <= 1'd1;
        end
        else if(opcode == 0 && cnt == cnt_push_burst && cnt != 0 && i_full_FIFO_request) begin
            o_read_request <= {3'd0, size, mark, address};
            o_push_request <= 1'd1;
        end
        else begin
            o_read_request <= 37'd0;
            o_push_request <= 1'd0;
        end
    end
end

endmodule

TILELINK/TILELINK_RAMv1.v
`include "RAM.v"
`include "FSM_a_slavev1.v"
`include "FIFO.v"
`include "FSM_d_masterv1.v"

module TILELINK_RAMv1(
    input clk, rst_n,
    
    output s_a_ready,
    input s_a_valid,
    input [100:0] i_data,

    output m_d_valid,
    input m_d_ready,
    output [100:0] o_data
);

//FIFO A
wire m_a_valid, m_a_ready;
wire [100:0] i_header_a_slave;
FIFO FIFO_inst0(
    .clk(clk),
    .rst_n(rst_n),
    .i_push(s_a_valid),
    .o_full(s_a_ready),
    .i_data(i_data),
    .o_empty(m_a_valid),
    .i_pop(m_a_ready),
    .o_data(i_header_a_slave)
);
assign m_a_validv1 = ~m_a_valid;

wire o_wen;
wire [95:0] o_packet;
wire [36:0] o_read_request;
wire o_push_request;
wire i_full_FIFO_request;
FSM_a_slavev1 FSM_a_slavev1_inst(
    .clk(clk),
    .rst_n(rst_n),
    .m_a_valid(m_a_validv1),
    .m_a_ready(m_a_ready),
    .i_header(i_header_a_slave),
    .o_wen(o_wen),
    .o_packet(o_packet),
    .o_read_request(o_read_request),
    .o_push_request(o_push_request),
    .i_full_FIFO_request(i_full_FIFO_request)
);
wire i_full_FIFO_requestv1;
assign i_full_FIFO_request = ~i_full_FIFO_requestv1;
wire o_empty_FIFO_request;
wire i_pop_FIFO_request;
wire [36:0] o_data_FIFO_request;
FIFO #(
    .d_width(37)
)
FIFO_inst2(
    .clk(clk),
    .rst_n(rst_n),
    .i_push(o_push_request),
    .o_full(i_full_FIFO_requestv1),
    .i_data(o_read_request),
    .o_empty(o_empty_FIFO_request),
    .i_pop(i_pop_FIFO_request),
    .o_data(o_data_FIFO_request)
);
wire o_empty_FIFO_requestv1;
assign o_empty_FIFO_requestv1 = ~o_empty_FIFO_request;
wire s_d_ready, s_d_valid;
wire [36:0] o_header;
FSM_d_masterv1 FSM_d_masterv1_inst(
    .clk(clk),
    .rst_n(rst_n),
    .i_empty_FIFO_request(o_empty_FIFO_requestv1),
    .i_read_request(o_data_FIFO_request),
    .o_pop_FIFO_request(i_pop_FIFO_request),
    .o_ren(i_ren),
    .o_read_address(i_read_address),
    .s_d_ready(s_d_readyv1),
    .s_d_valid(s_d_valid),
    .o_header(o_header)
);

//RAM
wire i_ren;
wire [31:0] i_read_address;
wire [63:0] o_data_ram;
RAM RAM_inst(
    .clk(clk),
    .rst_n(rst_n),
    .i_wen(o_wen),
    .i_write_address(o_packet[95:64]),
    .i_data(o_packet[63:0]),
    .i_ren(i_ren),
    .i_read_address(i_read_address),
    .o_data(o_data_ram)
);


assign s_d_readyv1 = ~s_d_ready;
//FIFO D

FIFO FIFO_inst1(
    .clk(clk),
    .rst_n(rst_n),
    .o_empty(m_d_valid),
    .i_pop(m_d_ready),
    .o_data(o_data),
    .o_full(s_d_ready),
    .i_push(s_d_valid),
    .i_data({o_header, o_data_ram})
);


endmodule

TILELINK/TILELINK_RAMv1_tb.v
`include "TILELINK_RAMv1.v"

module TILELINK_RAMv1_tb;

reg clk, rst_n;
    
wire s_a_ready;
reg s_a_valid;
reg [100:0] i_data;

wire m_d_valid;
reg m_d_ready;
wire [100:0] o_data;

TILELINK_RAMv1 dut(
    .clk(clk),
    .rst_n(rst_n),
    .s_a_ready(s_a_ready),
    .s_a_valid(s_a_valid),
    .i_data(i_data),
    .m_d_ready(m_d_ready),
    .m_d_valid(m_d_valid),
    .o_data(o_data)
);


always #5 clk = ~clk;

initial begin
    $dumpfile("TILELINK_RAMv1_tb.vcd");
    $dumpvars(0, TILELINK_RAMv1_tb);

    clk = 0;
    rst_n = 0;
    s_a_valid = 0;
    i_data = 0;
    m_d_ready = 0;

    #50 rst_n = 1;
    #10 m_d_ready = 1;

    #10 s_a_valid = 1;
        i_data = {6'b000110, 4'd15, 27'd0, 64'd5};
    #10 i_data = {6'b000110, 4'd15, 27'd0, 64'd6};
    #10 i_data = {6'b000110, 4'd15, 27'd0, 64'd7};
    #10 i_data = {6'b000110, 4'd15, 27'd0, 64'd8};
    #10 i_data = {6'b000110, 4'd15, 27'd0, 64'd9};
    #10 i_data = {6'b000110, 4'd15, 27'd0, 64'd10};
    #10 i_data = {6'b000110, 4'd15, 27'd0, 64'd11};
    #10 i_data = {6'b000110, 4'd15, 27'd0, 64'd12};
//    #10 s_a_valid = 0; i_data = 0;

    #10 s_a_valid = 1; i_data = {3'd4, 3'd6, 4'd15, 27'd0, 64'd0};
//   #10 s_a_valid = 0; i_data = 0;

    #10 s_a_valid = 1;
        i_data = {6'b000110, 4'd15, 27'd1, 64'd12};
    #10 i_data = {6'b000110, 4'd15, 27'd1, 64'd13};
    #10 i_data = {6'b000110, 4'd15, 27'd1, 64'd14};
    #10 i_data = {6'b000110, 4'd15, 27'd1, 64'd15};
    #10 i_data = {6'b000110, 4'd15, 27'd1, 64'd16};
    #10 i_data = {6'b000110, 4'd15, 27'd1, 64'd17};
    #10 i_data = {6'b000110, 4'd15, 27'd1, 64'd18};
    #10 i_data = {6'b000110, 4'd15, 27'd1, 64'd19};
//    #10 s_a_valid = 0; i_data = 0;

    #10 s_a_valid = 1; i_data = {3'd4, 3'd6, 4'd15, 27'd1, 64'd0};
    #10 s_a_valid = 0; i_data = 0;

    #300;
/*

    #10 s_a_valid = 1; i_data = {6'b00001, 4'd15, 27'd0, 64'd5};
    #10 s_a_valid = 1; i_data = {6'b00001, 4'd15, 27'd1, 64'd6};
    #10 s_a_valid = 1; i_data = {6'b00001, 4'd15, 27'd2, 64'd7};
    #10 s_a_valid = 1; i_data = {3'd4, 3'd1, 4'd15, 27'd1, 64'd0};
    #10 s_a_valid = 1; i_data = {3'd4, 3'd1, 4'd15, 27'd2, 64'd0};
    #10 s_a_valid = 1; i_data = {3'd4, 3'd1, 4'd15, 27'd0, 64'd0};
    #10 s_a_valid = 0; i_data = 0;
    #200
*/
    $finish;

end

endmodule

TILELINK/TILELINK_RAMv1_tb.vcd
$date
	Wed Jul 23 15:11:00 2025
$end
$version
	Icarus Verilog
$end
$timescale
	1s
$end
$scope module TILELINK_RAMv1_tb $end
$var wire 1 ! s_a_ready $end
$var wire 101 " o_data [100:0] $end
$var wire 1 # m_d_valid $end
$var reg 1 $ clk $end
$var reg 101 % i_data [100:0] $end
$var reg 1 & m_d_ready $end
$var reg 1 ' rst_n $end
$var reg 1 ( s_a_valid $end
$scope module dut $end
$var wire 1 $ clk $end
$var wire 101 ) i_data [100:0] $end
$var wire 1 * i_full_FIFO_request $end
$var wire 1 + m_a_validv1 $end
$var wire 1 & m_d_ready $end
$var wire 1 , o_empty_FIFO_requestv1 $end
$var wire 1 ' rst_n $end
$var wire 1 ( s_a_valid $end
$var wire 1 - s_d_readyv1 $end
$var wire 1 . s_d_valid $end
$var wire 1 / s_d_ready $end
$var wire 1 ! s_a_ready $end
$var wire 1 0 o_wen $end
$var wire 37 1 o_read_request [36:0] $end
$var wire 1 2 o_push_request $end
$var wire 96 3 o_packet [95:0] $end
$var wire 37 4 o_header [36:0] $end
$var wire 1 5 o_empty_FIFO_request $end
$var wire 64 6 o_data_ram [63:0] $end
$var wire 37 7 o_data_FIFO_request [36:0] $end
$var wire 101 8 o_data [100:0] $end
$var wire 1 # m_d_valid $end
$var wire 1 9 m_a_valid $end
$var wire 1 : m_a_ready $end
$var wire 1 ; i_ren $end
$var wire 32 < i_read_address [31:0] $end
$var wire 1 = i_pop_FIFO_request $end
$var wire 101 > i_header_a_slave [100:0] $end
$var wire 1 ? i_full_FIFO_requestv1 $end
$scope module FIFO_inst0 $end
$var wire 1 $ clk $end
$var wire 101 @ i_data [100:0] $end
$var wire 1 ( i_push $end
$var wire 101 A o_data [100:0] $end
$var wire 1 ' rst_n $end
$var wire 1 ! o_full $end
$var wire 1 9 o_empty $end
$var wire 1 : i_pop $end
$var reg 4 B r_ptr [3:0] $end
$var reg 4 C w_ptr [3:0] $end
$var integer 32 D i [31:0] $end
$upscope $end
$scope module FIFO_inst1 $end
$var wire 1 $ clk $end
$var wire 101 E i_data [100:0] $end
$var wire 1 & i_pop $end
$var wire 101 F o_data [100:0] $end
$var wire 1 ' rst_n $end
$var wire 1 / o_full $end
$var wire 1 # o_empty $end
$var wire 1 . i_push $end
$var reg 4 G r_ptr [3:0] $end
$var reg 4 H w_ptr [3:0] $end
$var integer 32 I i [31:0] $end
$upscope $end
$scope module FIFO_inst2 $end
$var wire 1 $ clk $end
$var wire 37 J o_data [36:0] $end
$var wire 1 ' rst_n $end
$var wire 1 ? o_full $end
$var wire 1 5 o_empty $end
$var wire 1 2 i_push $end
$var wire 1 = i_pop $end
$var wire 37 K i_data [36:0] $end
$var reg 4 L r_ptr [3:0] $end
$var reg 4 M w_ptr [3:0] $end
$var integer 32 N i [31:0] $end
$upscope $end
$scope module FSM_a_slavev1_inst $end
$var wire 1 $ clk $end
$var wire 1 * i_full_FIFO_request $end
$var wire 101 O i_header [100:0] $end
$var wire 1 + m_a_valid $end
$var wire 1 ' rst_n $end
$var wire 3 P size [2:0] $end
$var wire 3 Q opcode [2:0] $end
$var wire 4 R mark [3:0] $end
$var wire 64 S data [63:0] $end
$var wire 4 T cnt_push_burst [3:0] $end
$var wire 4 U beat [3:0] $end
$var wire 27 V address [26:0] $end
$var reg 4 W cnt [3:0] $end
$var reg 1 : m_a_ready $end
$var reg 96 X o_packet [95:0] $end
$var reg 1 2 o_push_request $end
$var reg 37 Y o_read_request [36:0] $end
$var reg 1 0 o_wen $end
$var reg 6 Z offset [5:0] $end
$upscope $end
$scope module FSM_d_masterv1_inst $end
$var wire 1 $ clk $end
$var wire 1 , i_empty_FIFO_request $end
$var wire 37 [ i_read_request [36:0] $end
$var wire 1 ' rst_n $end
$var wire 1 - s_d_ready $end
$var wire 3 \ size [2:0] $end
$var wire 3 ] opcode [2:0] $end
$var wire 4 ^ mark [3:0] $end
$var wire 4 _ cnt_read_burst [3:0] $end
$var wire 4 ` beat [3:0] $end
$var wire 27 a address [26:0] $end
$var reg 4 b cnt [3:0] $end
$var reg 1 c next_state $end
$var reg 37 d o_header [36:0] $end
$var reg 1 = o_pop_FIFO_request $end
$var reg 32 e o_read_address [31:0] $end
$var reg 1 ; o_ren $end
$var reg 6 f offset [5:0] $end
$var reg 37 g reg_read_request [36:0] $end
$var reg 1 . s_d_valid $end
$var reg 1 h state $end
$upscope $end
$scope module RAM_inst $end
$var wire 1 $ clk $end
$var wire 64 i i_data [63:0] $end
$var wire 32 j i_read_address [31:0] $end
$var wire 1 ; i_ren $end
$var wire 1 0 i_wen $end
$var wire 32 k i_write_address [31:0] $end
$var wire 1 ' rst_n $end
$var reg 64 l o_data [63:0] $end
$var integer 32 m i [31:0] $end
$upscope $end
$upscope $end
$upscope $end
$enddefinitions $end
#0
$dumpvars
b10000000000 m
bx l
b0 k
b0 j
b0 i
0h
b0 g
b0 f
b0 e
b0 d
0c
b0 b
b0 a
b1101 `
b0 _
b0 ^
b0 ]
b0 \
b0 [
b0 Z
b0 Y
b0 X
b1 W
b0 V
b1101 U
b0 T
b0 S
b0 R
b0 Q
b0 P
b0 O
b10000 N
b0 M
b0 L
b0 K
b0 J
b10000 I
b0 H
b0 G
b0 F
b0xxxxxxxxxxxxxxxxxxxxxxxxxxxxxxxxxxxxxxxxxxxxxxxxxxxxxxxxxxxxxxxx E
b10000 D
b0 C
b0 B
b0 A
b0 @
0?
b0 >
0=
b0 <
0;
0:
19
b0 8
b0 7
bx 6
15
b0 4
b0 3
02
b0 1
00
0/
0.
1-
0,
0+
1*
b0 )
0(
0'
0&
b0 %
0$
1#
b0 "
0!
$end
#5
b0 E
b0 6
b0 l
b10000 I
b10000 N
b10000 D
1$
#10
0$
#15
b10000 D
b10000 N
b10000 I
1$
#20
0$
#25
b10000 I
b10000 N
b10000 D
1$
#30
0$
#35
b10000 D
b10000 N
b10000 I
1$
#40
0$
#45
b10000 I
b10000 N
b10000 D
1$
#50
0$
1'
#55
1$
#60
0$
1&
#65
1$
#70
0$
b11011110000000000000000000000000000000000000000000000000000000000000000000000000000000000000000101 %
b11011110000000000000000000000000000000000000000000000000000000000000000000000000000000000000000101 )
b11011110000000000000000000000000000000000000000000000000000000000000000000000000000000000000000101 @
1(
#75
b101 i
b101 3
b101 X
10
1:
1+
09
b1000 T
b11 U
b110 P
b1111 R
b101 S
b1 C
b11011110000000000000000000000000000000000000000000000000000000000000000000000000000000000000000101 >
b11011110000000000000000000000000000000000000000000000000000000000000000000000000000000000000000101 A
b11011110000000000000000000000000000000000000000000000000000000000000000000000000000000000000000101 O
1$
#80
0$
b11011110000000000000000000000000000000000000000000000000000000000000000000000000000000000000000110 %
b11011110000000000000000000000000000000000000000000000000000000000000000000000000000000000000000110 )
b11011110000000000000000000000000000000000000000000000000000000000000000000000000000000000000000110 @
#85
b1000 k
b110 i
b10000000000000000000000000000000000000000000000000000000000000000110 3
b10000000000000000000000000000000000000000000000000000000000000000110 X
10
b1000 Z
b110 S
b10 W
b11011110000000000000000000000000000000000000000000000000000000000000000000000000000000000000000110 >
b11011110000000000000000000000000000000000000000000000000000000000000000000000000000000000000000110 A
b11011110000000000000000000000000000000000000000000000000000000000000000000000000000000000000000110 O
b1 B
b10 C
1$
#90
0$
b11011110000000000000000000000000000000000000000000000000000000000000000000000000000000000000000111 %
b11011110000000000000000000000000000000000000000000000000000000000000000000000000000000000000000111 )
b11011110000000000000000000000000000000000000000000000000000000000000000000000000000000000000000111 @
#95
b111 i
b10000 k
b100000000000000000000000000000000000000000000000000000000000000000111 3
b100000000000000000000000000000000000000000000000000000000000000000111 X
10
b111 S
b10000 Z
b11011110000000000000000000000000000000000000000000000000000000000000000000000000000000000000000111 >
b11011110000000000000000000000000000000000000000000000000000000000000000000000000000000000000000111 A
b11011110000000000000000000000000000000000000000000000000000000000000000000000000000000000000000111 O
b10 B
b11 C
b11 W
1$
#100
0$
b11011110000000000000000000000000000000000000000000000000000000000000000000000000000000000000001000 %
b11011110000000000000000000000000000000000000000000000000000000000000000000000000000000000000001000 )
b11011110000000000000000000000000000000000000000000000000000000000000000000000000000000000000001000 @
#105
b1000 i
b11000 k
b110000000000000000000000000000000000000000000000000000000000000001000 3
b110000000000000000000000000000000000000000000000000000000000000001000 X
10
b11000 Z
b1000 S
b100 W
b11011110000000000000000000000000000000000000000000000000000000000000000000000000000000000000001000 >
b11011110000000000000000000000000000000000000000000000000000000000000000000000000000000000000001000 A
b11011110000000000000000000000000000000000000000000000000000000000000000000000000000000000000001000 O
b11 B
b100 C
1$
#110
0$
b11011110000000000000000000000000000000000000000000000000000000000000000000000000000000000000001001 %
b11011110000000000000000000000000000000000000000000000000000000000000000000000000000000000000001001 )
b11011110000000000000000000000000000000000000000000000000000000000000000000000000000000000000001001 @
#115
b1001 i
b100000 k
b1000000000000000000000000000000000000000000000000000000000000000001001 3
b1000000000000000000000000000000000000000000000000000000000000000001001 X
10
b1001 S
b100000 Z
b11011110000000000000000000000000000000000000000000000000000000000000000000000000000000000000001001 >
b11011110000000000000000000000000000000000000000000000000000000000000000000000000000000000000001001 A
b11011110000000000000000000000000000000000000000000000000000000000000000000000000000000000000001001 O
b100 B
b101 C
b101 W
1$
#120
0$
b11011110000000000000000000000000000000000000000000000000000000000000000000000000000000000000001010 %
b11011110000000000000000000000000000000000000000000000000000000000000000000000000000000000000001010 )
b11011110000000000000000000000000000000000000000000000000000000000000000000000000000000000000001010 @
#125
b1010 i
b101000 k
b1010000000000000000000000000000000000000000000000000000000000000001010 3
b1010000000000000000000000000000000000000000000000000000000000000001010 X
10
b101000 Z
b1010 S
b110 W
b11011110000000000000000000000000000000000000000000000000000000000000000000000000000000000000001010 >
b11011110000000000000000000000000000000000000000000000000000000000000000000000000000000000000001010 A
b11011110000000000000000000000000000000000000000000000000000000000000000000000000000000000000001010 O
b101 B
b110 C
1$
#130
0$
b11011110000000000000000000000000000000000000000000000000000000000000000000000000000000000000001011 %
b11011110000000000000000000000000000000000000000000000000000000000000000000000000000000000000001011 )
b11011110000000000000000000000000000000000000000000000000000000000000000000000000000000000000001011 @
#135
b1011 i
b110000 k
b1100000000000000000000000000000000000000000000000000000000000000001011 3
b1100000000000000000000000000000000000000000000000000000000000000001011 X
10
b1011 S
b110000 Z
b11011110000000000000000000000000000000000000000000000000000000000000000000000000000000000000001011 >
b11011110000000000000000000000000000000000000000000000000000000000000000000000000000000000000001011 A
b11011110000000000000000000000000000000000000000000000000000000000000000000000000000000000000001011 O
b110 B
b111 C
b111 W
1$
#140
0$
b11011110000000000000000000000000000000000000000000000000000000000000000000000000000000000000001100 %
b11011110000000000000000000000000000000000000000000000000000000000000000000000000000000000000001100 )
b11011110000000000000000000000000000000000000000000000000000000000000000000000000000000000000001100 @
#145
b1100 i
b111000 k
b1110000000000000000000000000000000000000000000000000000000000000001100 3
b1110000000000000000000000000000000000000000000000000000000000000001100 X
10
b111000 Z
b1100 S
b1000 W
b11011110000000000000000000000000000000000000000000000000000000000000000000000000000000000000001100 >
b11011110000000000000000000000000000000000000000000000000000000000000000000000000000000000000001100 A
b11011110000000000000000000000000000000000000000000000000000000000000000000000000000000000000001100 O
b111 B
b1000 C
1$
#150
0$
b10011011110000000000000000000000000000000000000000000000000000000000000000000000000000000000000000000 %
b10011011110000000000000000000000000000000000000000000000000000000000000000000000000000000000000000000 )
b10011011110000000000000000000000000000000000000000000000000000000000000000000000000000000000000000000 @
#155
b0 i
b0 k
b0 3
b0 X
00
b100 Q
b0 S
b10011011110000000000000000000000000000000000000000000000000000000000000000000000000000000000000000000 >
b10011011110000000000000000000000000000000000000000000000000000000000000000000000000000000000000000000 A
b10011011110000000000000000000000000000000000000000000000000000000000000000000000000000000000000000000 O
b1000 B
b1001 C
b0 W
12
b1101111000000000000000000000000000 1
b1101111000000000000000000000000000 K
b1101111000000000000000000000000000 Y
1$
#160
0$
b11011110000000000000000000000000010000000000000000000000000000000000000000000000000000000000001100 %
b11011110000000000000000000000000010000000000000000000000000000000000000000000000000000000000001100 )
b11011110000000000000000000000000010000000000000000000000000000000000000000000000000000000000001100 @
#165
1c
1,
b1100 i
b1000000 k
05
b10000000000000000000000000000000000000000000000000000000000000000001100 3
b10000000000000000000000000000000000000000000000000000000000000000001100 X
10
b0 Z
b0 Q
b1 V
b1100 S
b1 M
b1101111000000000000000000000000000 7
b1101111000000000000000000000000000 J
b1101111000000000000000000000000000 [
b11101111000000000000000000000000000 1
b11101111000000000000000000000000000 K
b11101111000000000000000000000000000 Y
b1 W
b11011110000000000000000000000000010000000000000000000000000000000000000000000000000000000000001100 >
b11011110000000000000000000000000010000000000000000000000000000000000000000000000000000000000001100 A
b11011110000000000000000000000000010000000000000000000000000000000000000000000000000000000000001100 O
b1001 B
b1010 C
1$
#170
0$
b11011110000000000000000000000000010000000000000000000000000000000000000000000000000000000000001101 %
b11011110000000000000000000000000010000000000000000000000000000000000000000000000000000000000001101 )
b11011110000000000000000000000000010000000000000000000000000000000000000000000000000000000000001101 @
#175
b1101 i
b1001000 k
b1000 _
b10010000000000000000000000000000000000000000000000000000000000000001101 3
b10010000000000000000000000000000000000000000000000000000000000000001101 X
10
b11 `
b1101 S
b1000 Z
b110 \
b1111 ^
0c
b11011110000000000000000000000000010000000000000000000000000000000000000000000000000000000000001101 >
b11011110000000000000000000000000010000000000000000000000000000000000000000000000000000000000001101 A
b11011110000000000000000000000000010000000000000000000000000000000000000000000000000000000000001101 O
b1010 B
b1011 C
b10 W
02
b0 1
b0 K
b0 Y
b10 M
1=
b1101111000000000000000000000000000 g
1h
1$
#180
0$
b11011110000000000000000000000000010000000000000000000000000000000000000000000000000000000000001110 %
b11011110000000000000000000000000010000000000000000000000000000000000000000000000000000000000001110 )
b11011110000000000000000000000000010000000000000000000000000000000000000000000000000000000000001110 @
#185
b1110 i
b1010000 k
b10100000000000000000000000000000000000000000000000000000000000000001110 3
b10100000000000000000000000000000000000000000000000000000000000000001110 X
10
1c
b10000 Z
b1110 S
1.
0h
0=
b11101111000000000000000000000000000 7
b11101111000000000000000000000000000 J
b11101111000000000000000000000000000 [
b1 L
b11 W
b11011110000000000000000000000000010000000000000000000000000000000000000000000000000000000000001110 >
b11011110000000000000000000000000010000000000000000000000000000000000000000000000000000000000001110 A
b11011110000000000000000000000000010000000000000000000000000000000000000000000000000000000000001110 O
b1011 B
b1100 C
b11011110000000000000000000000000000000000000000000000000000000000000000000000000000000000000000000 E
b1101111000000000000000000000000000 4
b1101111000000000000000000000000000 d
1$
#190
0$
b11011110000000000000000000000000010000000000000000000000000000000000000000000000000000000000001111 %
b11011110000000000000000000000000010000000000000000000000000000000000000000000000000000000000001111 )
b11011110000000000000000000000000010000000000000000000000000000000000000000000000000000000000001111 @
#195
1;
b1111 i
b1011000 k
b10110000000000000000000000000000000000000000000000000000000000000001111 3
b10110000000000000000000000000000000000000000000000000000000000000001111 X
10
0#
b1111 S
b11000 Z
b1 ]
1c
b11011110000000000000000000000000010000000000000000000000000000000000000000000000000000000000001111 >
b11011110000000000000000000000000010000000000000000000000000000000000000000000000000000000000001111 A
b11011110000000000000000000000000010000000000000000000000000000000000000000000000000000000000001111 O
b1100 B
b1101 C
b100 W
1=
b11101111000000000000000000000000000 g
1h
0.
b1 H
b11011110000000000000000000000000000000000000000000000000000000000000000000000000000000000000000000 "
b11011110000000000000000000000000000000000000000000000000000000000000000000000000000000000000000000 8
b11011110000000000000000000000000000000000000000000000000000000000000000000000000000000000000000000 F
1$
#200
0$
b11011110000000000000000000000000010000000000000000000000000000000000000000000000000000000000010000 %
b11011110000000000000000000000000010000000000000000000000000000000000000000000000000000000000010000 )
b11011110000000000000000000000000010000000000000000000000000000000000000000000000000000000000010000 @
#205
b1000 <
b1000 e
b1000 j
0,
b10000 i
b1100000 k
1#
15
b11000000000000000000000000000000000000000000000000000000000000000010000 3
b11000000000000000000000000000000000000000000000000000000000000000010000 X
10
b1000 f
b100000 Z
b10000 S
b0 "
b0 8
b0 F
b1 G
1.
b1 b
0=
b0 7
b0 J
b0 [
b10 L
b101 W
b11011110000000000000000000000000010000000000000000000000000000000000000000000000000000000000010000 >
b11011110000000000000000000000000010000000000000000000000000000000000000000000000000000000000010000 A
b11011110000000000000000000000000010000000000000000000000000000000000000000000000000000000000010000 O
b1101 B
b1110 C
b101 6
b101 l
b111011110000000000000000000000000000000000000000000000000000000000000000000000000000000000000000101 E
b11101111000000000000000000000000000 4
b11101111000000000000000000000000000 d
1$
#210
0$
b11011110000000000000000000000000010000000000000000000000000000000000000000000000000000000000010001 %
b11011110000000000000000000000000010000000000000000000000000000000000000000000000000000000000010001 )
b11011110000000000000000000000000010000000000000000000000000000000000000000000000000000000000010001 @
