TILELINK/RAM.v
module RAM(
    input clk, rst_n,

    input i_wen,
    input [31:0] i_write_address,
    input [63:0] i_data,

    input i_ren,
    input [31:0] i_read_address,
    output reg [63:0] o_data
);

reg [7:0] mem_data [0:1023];
integer i;
initial begin
    for(i = 0; i < 1024; i = i + 1) begin
        mem_data[i] = 8'd0;
    end
end

always @(posedge clk) begin
    if(i_wen) begin
        mem_data[i_write_address] <= i_data[7:0];
        mem_data[i_write_address + 1] <= i_data[15:8];
        mem_data[i_write_address + 2] <= i_data[23:16];
        mem_data[i_write_address + 3] <= i_data[31:24];
        mem_data[i_write_address + 4] <= i_data[39:32];
        mem_data[i_write_address + 5] <= i_data[47:40];
        mem_data[i_write_address + 6] <= i_data[55:48];
        mem_data[i_write_address + 7] <= i_data[63:56];
    end
end

always @(posedge clk) begin
    o_data <= 64'd0;
    if(i_ren) begin
        o_data[7:0] <= mem_data[i_read_address];
        o_data[15:8] <= mem_data[i_read_address + 1];
        o_data[23:16] <= mem_data[i_read_address + 2];
        o_data[31:24] <= mem_data[i_read_address + 3];
        o_data[39:32] <= mem_data[i_read_address + 4];
        o_data[47:40] <= mem_data[i_read_address + 5];
        o_data[55:48] <= mem_data[i_read_address + 6];
        o_data[63:56] <= mem_data[i_read_address + 7];
    end
end


endmodule

AXI/LANE_EN_WRITE.v
module LANE_EN_WRITE(
    input clk, rst_n,
    input [63:0] i_data,
    input [7:0] byte_enable,
    output reg [63:0] o_data
);

    always @(posedge clk or negedge rst_n) begin
        if (!rst_n) begin
            o_data <= 64'd0;
        end else begin
            if (byte_enable[0]) o_data[7:0]   <= i_data[7:0];
            if (byte_enable[1]) o_data[15:8]  <= i_data[15:8];
            if (byte_enable[2]) o_data[23:16] <= i_data[23:16];
            if (byte_enable[3]) o_data[31:24] <= i_data[31:24];
            if (byte_enable[4]) o_data[39:32] <= i_data[39:32];
            if (byte_enable[5]) o_data[47:40] <= i_data[47:40];
            if (byte_enable[6]) o_data[55:48] <= i_data[55:48];
            if (byte_enable[7]) o_data[63:56] <= i_data[63:56];
        end
    end

endmodule

AXI/DECODE_ADDR.v
module DECODE_ADDR(
    input clk, rst_n,
    input [2:0] size,
    input [31:0] addr,
    input select,
    output reg [31:0] addr_decode
);

wire [7:0] offset;
assign offset = 1 << size;

always @(posedge clk or negedge rst_n) begin
    if(!rst_n) begin
        addr_decode <= 0;
    end
    else begin
        if(select == 0) begin
            addr_decode <= addr;
        end
        else begin
            addr_decode <= addr_decode + offset;
        end
    end
end

endmodule

AXI/FSM_MASTER_READ.v
module FSM_MASTER_READ(
    input clk, rst_n,

    input m_arvalid,
    output reg m_arready,

    input [1:0] m_arburst,
    input [7:0] m_arlen,
    
    input m_rvalid,
    output m_rready,

    output m_rlast,

    output [1:0] m_rresp,

    output select_address,

    output reg o_ren
);

localparam IDLE = 0,
           TRANSFER = 1;

reg state, next_state;
reg [7:0] cnt_read;
always @(*) begin
    case(state)
        IDLE: next_state = (m_arvalid) ? TRANSFER : IDLE;
        TRANSFER: next_state = (cnt_read == m_arlen + 1) ? IDLE : TRANSFER;
    endcase
end

always @(posedge clk or negedge rst_n) begin
    if(!rst_n) begin
        state <= IDLE;
    end
    else begin
        state <= next_state;
    end
end

//m_arready
always @(*) begin
    m_arready = 0;
    if(state == TRANSFER && cnt_read == m_arlen + 1) begin
        m_arready = 1;
    end
end

//cnt_read
always @(posedge clk or negedge rst_n) begin
    if(!rst_n) begin
        cnt_read <= 0;
    end
    else begin
        if(state == TRANSFER && !m_rlast_stage0) begin
            cnt_read <= cnt_read + 1;
        end
        else if(m_rlast_stage0) begin
            cnt_read <= 0;
        end
    end
end

//m_rready
reg m_rready_stage0;
reg m_rready_stage1;
always @(posedge clk or negedge rst_n) begin
    if(!rst_n) begin
        m_rready_stage0 <= 0;
    end
    else begin
        if(state == TRANSFER && cnt_read != m_arlen + 1) begin
            m_rready_stage0 <= 1;
        end
        else m_rready_stage0 <= 0;
    end
end



//m_rlast
reg m_rlast_stage0;
reg m_rlast_stage1;
always @(posedge clk or negedge rst_n) begin
    if(!rst_n) begin
        m_rlast_stage0 <= 0;
    end
    else begin
        if(state == TRANSFER && cnt_read == m_arlen) begin
            m_rlast_stage0 <= 1;
        end
        else m_rlast_stage0 <= 0;
    end
end

//m_rresp
reg [1:0] m_rresp_stage0;
reg [1:0] m_rresp_stage1;
always @(posedge clk or negedge rst_n) begin
    if(!rst_n) begin
        m_rresp_stage0 <= 0;
    end
    else begin
        if(state == TRANSFER) begin
            m_rresp_stage0 <= 2'b00; //okay
        end
        else m_rresp_stage0 <= 2'b11; //error
    end
end

/*
always @(posedge clk or negedge rst_n) begin
    if(!rst_n) begin
        m_rready_stage1 <= 0;
        m_rlast_stage1 <= 0;
        m_rresp_stage1 <= 0;
    end
    else begin
        m_rready_stage1 <= m_rready_stage0;
        m_rlast_stage1 <= m_rlast_stage0;
        m_rresp_stage1 <= m_rresp_stage0;
    end
end*/

assign m_rready = m_rready_stage0;
assign m_rlast  = m_rlast_stage0;
assign m_rresp  = m_rresp_stage0;
assign select_address = (state == TRANSFER && m_arburst == 2'b01);


always @(*) begin
    o_ren = 0;
    if(state == TRANSFER) begin
        o_ren = 1;
    end
end

endmodule

AXI/BRESP.v
module BRESP(
    input clk, rst_n,
    input [2:0] b_resp,
    input m_bvalid,
    output reg m_bready,
    output reg  [1:0] m_bresp
);

always @(*) begin
    m_bready = 0;
    m_bresp = 0;
    if(b_resp == 3'b100 && m_bvalid) begin
        m_bready = 1;
        m_bresp = 0;
    end
end

endmodule

AXI/FSM_MASTER_WRITE.v
module FSM_MASTER_WRITE(
    input clk, rst_n,
    
    input m_awvalid,
    output reg m_awready,

    input [1:0] m_awburst,
    input [7:0] m_awlen,
    
    input m_wvalid,
    output reg m_wready,
    input m_wlast,

    output reg [2:0] b_reps,

    output reg select_address,

    output reg o_wen
);

localparam IDLE = 0,
           TRANSFER = 1;

reg state, next_state;
reg [7:0] cnt_push;
always @(*) begin
    case(state)
        IDLE: next_state = (m_awvalid && m_wvalid) ? TRANSFER : IDLE;
        TRANSFER: next_state = (m_wlast) ? IDLE : TRANSFER;
    endcase
end

always @(posedge clk or negedge rst_n) begin
    if(!rst_n) begin
        state <= IDLE;
    end
    else begin
        state <= next_state;
    end
end

//m_awready
always @(*) begin
    m_awready = 0;
    if(m_wlast && state == TRANSFER) begin
        m_awready = 1;
    end
end

//cnt_push
always @(posedge clk or negedge rst_n) begin
    if(!rst_n) begin
        cnt_push <= 0;
    end
    else begin
        if((state == TRANSFER && !m_wlast)|| (state == IDLE && m_awvalid && m_wvalid)) begin
            cnt_push <= cnt_push + 1;
        end
        else if(state == TRANSFER && m_wlast) begin
            cnt_push <= 0;
        end
    end
end

//m_wready
always @(*) begin
    m_wready = 0;
    if(state == TRANSFER || (state == IDLE && m_awvalid && m_wvalid)) begin
        m_wready = 1;
    end
end

//b_reps
always @(*) begin
    if(m_wlast && cnt_push == m_awlen && state == TRANSFER) begin
        b_reps = 3'b100; //okay
    end
    else begin
        b_reps = 3'b111; //error
    end
end

//select_address
always @(*) begin
    select_address = 0;
    if(state == TRANSFER && m_awburst == 2'b01) begin
        select_address = 1;
    end
end

always @(posedge clk or negedge rst_n) begin
    if(!rst_n) begin
        o_wen <= 0;
    end
    else begin
        if(state == TRANSFER || (state == IDLE && m_awvalid && m_wvalid)) begin
            o_wen <= 1;
        end
        else o_wen <= 0;
    end
end

endmodule

AXI/FIFO.v
module FIFO #(
    parameter d_width = 101
)
(
    input clk, rst_n,
    input i_push, i_pop,
    input [d_width -1 : 0] i_data,

    output o_empty,
    output o_full,
    output [d_width -1 : 0] o_data
);

reg [3:0] w_ptr, r_ptr;
reg [d_width -1 : 0] mem_data [0:15];
integer i;
always @(posedge clk or negedge rst_n) begin
    if(!rst_n) begin
        for(i = 0; i < 16; i = i + 1) begin
            mem_data[i] <= 101'd0;
        end
        w_ptr <= 0;
        r_ptr <= 0;
    end
    else begin
        if(i_push && !o_full) begin
            mem_data[w_ptr] <= i_data;
            w_ptr <= w_ptr + 1;
        end
        if(i_pop && !o_empty) begin
            r_ptr <= r_ptr + 1;
        end
    end
end

assign o_data = mem_data[r_ptr];
assign o_full = ((w_ptr + 1) == r_ptr) ? 1 : 0;
assign o_empty = (w_ptr == r_ptr) ? 1 : 0;

endmodule

AXI/AXI_RAM.v
`include "FSM_MASTER_READ.v"
`include "FSM_MASTER_WRITE.v"
`include "BRESP.v"
`include "FIFO.v"
`include "RAM.v"
`include "LANE_EN_WRITE.v"
`include "DECODE_ADDR.v"

module AXI_RAM(
    input clk, rst_n,

    //S_AW
    output s_awready,
    input s_awvalid,
    input [1:0] s_awburst,
    input [2:0] s_awsize,
    input [7:0] s_awlen,
    input [31:0] s_awaddr,

    //S_W
    output s_wready,
    input s_wvalid,
    input s_wlast,
    input [63:0] s_wdata,
    input [7:0] s_wstrb,

    //S_B
    output s_bvalid,
    input s_bready,
    output [1:0] s_bresp,

    //S_AR
    output s_arready,
    input s_arvalid,
    input [1:0] s_arburst,
    input [2:0] s_arsize,
    input [7:0] s_arlen,
    input [31:0] s_araddr,

    //S_R
    output s_rvalid,
    input s_rready,
    output s_rlast,
    output [63:0] s_rdata,
    output [1:0] s_rresp
);

//AW
wire m_awready, m_awvalid;
wire empty_AW;
assign m_awvalid = ~empty_AW;
wire [44:0] o_data_AW;
FIFO #(
    .d_width(45)
)
FIFO_AW(
    .clk(clk),
    .rst_n(rst_n),
    .i_push(s_awvalid),
    .i_pop(m_awready),
    .i_data({s_awburst, s_awlen, s_awsize, s_awaddr}),
    .o_empty(empty_AW),
    .o_full(s_awready),
    .o_data(o_data_AW)
);

//W
wire m_wready, m_wvalid;
wire empty_W;
assign m_wvalid = ~empty_W;
wire [72:0] o_data_W;
FIFO #(
    .d_width(73)
)
FIFO_W(
    .clk(clk),
    .rst_n(rst_n),
    .i_push(s_wvalid),
    .i_pop(m_wready),
    .i_data({s_wlast, s_wdata, s_wstrb}),
    .o_empty(empty_W),
    .o_full(s_wready),
    .o_data(o_data_W)
);

//B
wire [1:0] m_bresp;
wire m_bvalid, m_bready;
wire full_B;
assign m_bvalid = ~full_B;
FIFO #(
    .d_width(2)
)
FIFO_B(
    .clk(clk),
    .rst_n(rst_n),
    .i_push(m_bready),
    .i_pop(s_bready),
    .i_data(m_bresp),
    .o_empty(s_bvalid),
    .o_full(full_B),
    .o_data(s_bresp)
);

//AR
wire m_arready, m_arvalid;
wire empty_AR;
assign m_arvalid = ~empty_AR;
wire [44:0] o_data_AR;
FIFO #(
    .d_width(45)
)
FIFO_AR(
    .clk(clk),
    .rst_n(rst_n),
    .i_push(s_arvalid),
    .i_pop(m_arready),
    .i_data({s_arburst, s_arlen, s_arsize, s_araddr}),
    .o_empty(empty_AR),
    .o_full(s_arready),
    .o_data(o_data_AR)
);

//R
wire m_rready, m_rvalid;
wire m_rlast;
wire full_R;
assign m_rvalid = ~full_R;
wire [1:0] m_rresp;
wire [63:0] m_rdata;
FIFO #(
    .d_width(67)
)
FIFO_R(
    .clk(clk),
    .rst_n(rst_n),
    .i_push(m_rready),
    .i_pop(s_rready),
    .i_data({m_rlast, m_rdata, m_rresp}),
    .o_empty(s_rvalid),
    .o_full(full_R),
    .o_data({s_rlast, s_rdata, s_rresp})
);

wire [2:0] b_resp;
wire select_address_write;
wire wen_RAM;
FSM_MASTER_WRITE FSM_MASTER_WRITE_inst(
    .clk(clk),
    .rst_n(rst_n),
    .m_awvalid(m_awvalid),
    .m_awready(m_awready),
    .m_awburst(o_data_AW[44:43]),
    .m_awlen(o_data_AW[42:35]),
    .m_wvalid(m_wvalid),
    .m_wready(m_wready),
    .m_wlast(o_data_W[72]),
    .b_reps(b_resp),
    .select_address(select_address_write),
    .o_wen(wen_RAM)
);
wire [31:0] address_write_RAM;
DECODE_ADDR DECODE_ADDR_inst0(
    .clk(clk),
    .rst_n(rst_n),
    .size(o_data_AW[34:32]),
    .addr(o_data_AW[31:0]),
    .select(select_address_write),
    .addr_decode(address_write_RAM)
);

BRESP BRESP_inst(
    .clk(clk),
    .rst_n(rst_n),
    .b_resp(b_resp),
    .m_bvalid(m_bvalid),
    .m_bready(m_bready),
    .m_bresp(m_bresp)
);

wire select_address_read;
wire ren_RAM;
FSM_MASTER_READ FSM_MASTER_READ_inst(
    .clk(clk),
    .rst_n(rst_n),
    .m_arvalid(m_arvalid),
    .m_arready(m_arready),
    .m_arburst(o_data_AR[44:43]),
    .m_arlen(o_data_AR[42:35]),
    .m_rvalid(m_rvalid),
    .m_rready(m_rready),
    .m_rlast(m_rlast),
    .m_rresp(m_rresp),
    .select_address(select_address_read),
    .o_ren(ren_RAM)
);
wire [31:0] address_read_RAM;
DECODE_ADDR DECODE_ADDR_inst1(
    .clk(clk),
    .rst_n(rst_n),
    .size(o_data_AR[34:32]),
    .addr(o_data_AR[31:0]),
    .select(select_address_read),
    .addr_decode(address_read_RAM)
);

wire [63:0] write_data_RAM;
LANE_EN_WRITE LANE_EN_WRITE_inst(
    .clk(clk),
    .rst_n(rst_n),
    .i_data(o_data_W[71:8]),
    .byte_enable(o_data_W[7:0]),
    .o_data(write_data_RAM)
);

RAM RAM_inst(
    .clk(clk),
    .rst_n(rst_n),
    .i_wen(wen_RAM),
    .i_write_address(address_write_RAM),
    .i_data(write_data_RAM),
    .i_ren(ren_RAM),
    .i_read_address(address_read_RAM),
    .o_data(m_rdata)
);


endmodule

AXI/AXI_RAM_tb.v
`include "AXI_RAM.v"

module AXI_RAM_tb;

reg clk, rst_n;

    //S_AW
    wire s_awready;
    reg s_awvalid;
    reg [1:0] s_awburst;
    reg [2:0] s_awsize;
    reg [7:0] s_awlen;
    reg [31:0] s_awaddr;

    //S_W
    wire s_wready;
    reg s_wvalid;
    reg s_wlast;
    reg [63:0] s_wdata;
    reg [7:0] s_wstrb;

    //S_B
    wire s_bvalid;
    reg s_bready;
    wire [1:0] s_bresp;

    //S_AR
    wire s_arready;
    reg s_arvalid;
    reg [1:0] s_arburst;
    reg [2:0] s_arsize;
    reg [7:0] s_arlen;
    reg [31:0] s_araddr;

    //S_R
    wire s_rvalid;
    reg s_rready;
    wire s_rlast;
    wire [63:0] s_rdata;
    wire [1:0] s_rresp;

AXI_RAM dut(
    .clk(clk),
    .rst_n(rst_n),

    .s_awready(s_awready),
    .s_awvalid(s_awvalid),
    .s_awburst(s_awburst),
    .s_awsize(s_awsize),
    .s_awlen(s_awlen),
    .s_awaddr(s_awaddr),

    .s_wready(s_wready),
    .s_wvalid(s_wvalid),
    .s_wlast(s_wlast),
    .s_wdata(s_wdata),
    .s_wstrb(s_wstrb),

    .s_bvalid(s_bvalid),
    .s_bready(s_bready),
    .s_bresp(s_bresp),

    .s_arready(s_arready),
    .s_arvalid(s_arvalid),
    .s_arburst(s_arburst),
    .s_arsize(s_arsize),
    .s_arlen(s_arlen),
    .s_araddr(s_araddr),

    .s_rvalid(s_rvalid),
    .s_rready(s_rready),
    .s_rlast(s_rlast),
    .s_rdata(s_rdata),
    .s_rresp(s_rresp)
);

always #5 clk = ~clk;

initial begin
    $dumpfile("AXI_RAM_tb.vcd");
    $dumpvars(0, AXI_RAM_tb);

    clk = 0;
    rst_n = 0;

    s_awvalid = 0;
    s_awburst = 0;
    s_awsize = 0;
    s_awlen = 0;
    s_awaddr = 0;

    s_wvalid = 0;
    s_wlast = 0;
    s_wdata = 0;
    s_wstrb = 0;

    s_bready = 0;

    s_arvalid = 0;
    s_arburst = 0;
    s_arsize = 0;
    s_arlen = 0;
    s_araddr = 0;

    s_rready = 0;

    #30 rst_n = 1;
    //
    #10 
    s_awvalid = 1;
    s_awburst = 1;
    s_awsize = 3;
    s_awlen = 7;
    s_awaddr = 0;

    s_wvalid = 1;
    s_wlast = 0;
    s_wdata = 5;
    s_wstrb = 8'b11111111;

    #10 
    s_awvalid = 0;
    s_wvalid = 1;
    s_wlast = 0;
    s_wdata = 6;
    s_wstrb = 8'b11111111;

    #10 
    s_awvalid = 0;
    s_wvalid = 1;
    s_wlast = 0;
    s_wdata = 7;
    s_wstrb = 8'b11111111;

    #10 
    s_awvalid = 0;
    s_wvalid = 1;
    s_wlast = 0;
    s_wdata = 8;
    s_wstrb = 8'b11111111;

    #10 
    s_awvalid = 0;
    s_wvalid = 1;
    s_wlast = 0;
    s_wdata = 9;
    s_wstrb = 8'b11111111;

    #10 
    s_awvalid = 0;
    s_wvalid = 1;
    s_wlast = 0;
    s_wdata = 10;
    s_wstrb = 8'b11111111;

    #10 
    s_awvalid = 0;
    s_wvalid = 1;
    s_wlast = 0;
    s_wdata = 11;
    s_wstrb = 8'b11111111;

    #10
    s_awvalid = 0;
    s_wvalid = 1;
    s_wlast = 1;
    s_wdata = 12;
    s_wstrb = 8'b11111111;
//

    #10
    s_wvalid = 0;
    s_bready = 1;

    s_rready = 1;
    s_arvalid = 1;
    s_arburst = 1;
    s_arsize = 3;
    s_arlen = 7;
    s_araddr = 0;


//
    #10 
    s_arvalid = 0;
    s_awvalid = 1;
    s_awburst = 1;
    s_awsize = 3;
    s_awlen = 7;
    s_awaddr = 64;

    s_wvalid = 1;
    s_wlast = 0;
    s_wdata = 13;
    s_wstrb = 8'b11111111;

    #10 
    s_awvalid = 0;
    s_wvalid = 1;
    s_wlast = 0;
    s_wdata = 14;
    s_wstrb = 8'b11111111;

    #10 
    s_awvalid = 0;
    s_wvalid = 1;
    s_wlast = 0;
    s_wdata = 15;
    s_wstrb = 8'b11111111;

    #10 
    s_awvalid = 0;
    s_wvalid = 1;
    s_wlast = 0;
    s_wdata = 16;
    s_wstrb = 8'b11111111;
    #10 
    s_awvalid = 0;
    s_wvalid = 1;
    s_wlast = 0;
    s_wdata = 17;
    s_wstrb = 8'b11111111;
    #10 
    s_awvalid = 0;
    s_wvalid = 1;
    s_wlast = 0;
    s_wdata = 18;
    s_wstrb = 8'b11111111;
    #10 
    s_awvalid = 0;
    s_wvalid = 1;
    s_wlast = 0;
    s_wdata = 19;
    s_wstrb = 8'b11111111;
    #10 
    s_awvalid = 0;
    s_wvalid = 1;
    s_wlast = 1;
    s_wdata = 20;
    s_wstrb = 8'b11111111;

    #10
    s_wvalid = 0;
    s_rready = 1;
    s_arvalid = 1;
    s_arburst = 1;
    s_arsize = 3;
    s_arlen = 7;
    s_araddr = 64;
    #10 s_arvalid = 0;
    #300;
    $finish;

end

endmodule

AXI/AXI_RAM_tb.vcd
$date
	Wed Jul 23 15:08:38 2025
$end
$version
	Icarus Verilog
$end
$timescale
	1s
$end
$scope module AXI_RAM_tb $end
$var wire 1 ! s_wready $end
$var wire 1 " s_rvalid $end
$var wire 2 # s_rresp [1:0] $end
$var wire 1 $ s_rlast $end
$var wire 64 % s_rdata [63:0] $end
$var wire 1 & s_bvalid $end
$var wire 2 ' s_bresp [1:0] $end
$var wire 1 ( s_awready $end
$var wire 1 ) s_arready $end
$var reg 1 * clk $end
$var reg 1 + rst_n $end
$var reg 32 , s_araddr [31:0] $end
$var reg 2 - s_arburst [1:0] $end
$var reg 8 . s_arlen [7:0] $end
$var reg 3 / s_arsize [2:0] $end
$var reg 1 0 s_arvalid $end
$var reg 32 1 s_awaddr [31:0] $end
$var reg 2 2 s_awburst [1:0] $end
$var reg 8 3 s_awlen [7:0] $end
$var reg 3 4 s_awsize [2:0] $end
$var reg 1 5 s_awvalid $end
$var reg 1 6 s_bready $end
$var reg 1 7 s_rready $end
$var reg 64 8 s_wdata [63:0] $end
$var reg 1 9 s_wlast $end
$var reg 8 : s_wstrb [7:0] $end
$var reg 1 ; s_wvalid $end
$scope module dut $end
$var wire 1 * clk $end
$var wire 1 < m_arvalid $end
$var wire 1 = m_awvalid $end
$var wire 1 > m_bvalid $end
$var wire 1 ? m_rvalid $end
$var wire 1 @ m_wvalid $end
$var wire 1 + rst_n $end
$var wire 32 A s_araddr [31:0] $end
$var wire 2 B s_arburst [1:0] $end
$var wire 8 C s_arlen [7:0] $end
$var wire 3 D s_arsize [2:0] $end
$var wire 1 0 s_arvalid $end
$var wire 32 E s_awaddr [31:0] $end
$var wire 2 F s_awburst [1:0] $end
$var wire 8 G s_awlen [7:0] $end
$var wire 3 H s_awsize [2:0] $end
$var wire 1 5 s_awvalid $end
$var wire 1 6 s_bready $end
$var wire 1 7 s_rready $end
$var wire 64 I s_wdata [63:0] $end
$var wire 1 9 s_wlast $end
$var wire 8 J s_wstrb [7:0] $end
$var wire 1 ; s_wvalid $end
$var wire 64 K write_data_RAM [63:0] $end
$var wire 1 L wen_RAM $end
$var wire 1 M select_address_write $end
$var wire 1 N select_address_read $end
$var wire 1 ! s_wready $end
$var wire 1 " s_rvalid $end
$var wire 2 O s_rresp [1:0] $end
$var wire 1 $ s_rlast $end
$var wire 64 P s_rdata [63:0] $end
$var wire 1 & s_bvalid $end
$var wire 2 Q s_bresp [1:0] $end
$var wire 1 ( s_awready $end
$var wire 1 ) s_arready $end
$var wire 1 R ren_RAM $end
$var wire 73 S o_data_W [72:0] $end
$var wire 45 T o_data_AW [44:0] $end
$var wire 45 U o_data_AR [44:0] $end
$var wire 1 V m_wready $end
$var wire 2 W m_rresp [1:0] $end
$var wire 1 X m_rready $end
$var wire 1 Y m_rlast $end
$var wire 64 Z m_rdata [63:0] $end
$var wire 2 [ m_bresp [1:0] $end
$var wire 1 \ m_bready $end
$var wire 1 ] m_awready $end
$var wire 1 ^ m_arready $end
$var wire 1 _ full_R $end
$var wire 1 ` full_B $end
$var wire 1 a empty_W $end
$var wire 1 b empty_AW $end
$var wire 1 c empty_AR $end
$var wire 3 d b_resp [2:0] $end
$var wire 32 e address_write_RAM [31:0] $end
$var wire 32 f address_read_RAM [31:0] $end
$scope module BRESP_inst $end
$var wire 1 * clk $end
$var wire 1 > m_bvalid $end
$var wire 1 + rst_n $end
$var wire 3 g b_resp [2:0] $end
$var reg 1 \ m_bready $end
$var reg 2 h m_bresp [1:0] $end
$upscope $end
$scope module DECODE_ADDR_inst0 $end
$var wire 32 i addr [31:0] $end
$var wire 1 * clk $end
$var wire 1 + rst_n $end
$var wire 3 j size [2:0] $end
$var wire 1 M select $end
$var wire 8 k offset [7:0] $end
$var reg 32 l addr_decode [31:0] $end
$upscope $end
$scope module DECODE_ADDR_inst1 $end
$var wire 32 m addr [31:0] $end
$var wire 1 * clk $end
$var wire 1 + rst_n $end
$var wire 3 n size [2:0] $end
$var wire 1 N select $end
$var wire 8 o offset [7:0] $end
$var reg 32 p addr_decode [31:0] $end
$upscope $end
$scope module FIFO_AR $end
$var wire 1 * clk $end
$var wire 45 q i_data [44:0] $end
$var wire 1 0 i_push $end
$var wire 45 r o_data [44:0] $end
$var wire 1 + rst_n $end
$var wire 1 ) o_full $end
$var wire 1 c o_empty $end
$var wire 1 ^ i_pop $end
$var reg 4 s r_ptr [3:0] $end
$var reg 4 t w_ptr [3:0] $end
$var integer 32 u i [31:0] $end
$upscope $end
$scope module FIFO_AW $end
$var wire 1 * clk $end
$var wire 45 v i_data [44:0] $end
$var wire 1 5 i_push $end
$var wire 45 w o_data [44:0] $end
$var wire 1 + rst_n $end
$var wire 1 ( o_full $end
$var wire 1 b o_empty $end
$var wire 1 ] i_pop $end
$var reg 4 x r_ptr [3:0] $end
$var reg 4 y w_ptr [3:0] $end
$var integer 32 z i [31:0] $end
$upscope $end
$scope module FIFO_B $end
$var wire 1 * clk $end
$var wire 2 { i_data [1:0] $end
$var wire 1 6 i_pop $end
$var wire 1 \ i_push $end
$var wire 2 | o_data [1:0] $end
$var wire 1 + rst_n $end
$var wire 1 ` o_full $end
$var wire 1 & o_empty $end
$var reg 4 } r_ptr [3:0] $end
$var reg 4 ~ w_ptr [3:0] $end
$var integer 32 !" i [31:0] $end
$upscope $end
$scope module FIFO_R $end
$var wire 1 * clk $end
$var wire 67 "" i_data [66:0] $end
$var wire 1 7 i_pop $end
$var wire 67 #" o_data [66:0] $end
$var wire 1 + rst_n $end
$var wire 1 _ o_full $end
$var wire 1 " o_empty $end
$var wire 1 X i_push $end
$var reg 4 $" r_ptr [3:0] $end
$var reg 4 %" w_ptr [3:0] $end
$var integer 32 &" i [31:0] $end
$upscope $end
$scope module FIFO_W $end
$var wire 1 * clk $end
$var wire 73 '" i_data [72:0] $end
$var wire 1 ; i_push $end
$var wire 73 (" o_data [72:0] $end
$var wire 1 + rst_n $end
$var wire 1 ! o_full $end
$var wire 1 a o_empty $end
$var wire 1 V i_pop $end
$var reg 4 )" r_ptr [3:0] $end
$var reg 4 *" w_ptr [3:0] $end
$var integer 32 +" i [31:0] $end
$upscope $end
$scope module FSM_MASTER_READ_inst $end
$var wire 1 * clk $end
$var wire 2 ," m_arburst [1:0] $end
$var wire 8 -" m_arlen [7:0] $end
$var wire 1 < m_arvalid $end
$var wire 1 X m_rready $end
$var wire 1 ? m_rvalid $end
$var wire 1 + rst_n $end
$var wire 1 N select_address $end
$var wire 2 ." m_rresp [1:0] $end
$var wire 1 Y m_rlast $end
$var reg 8 /" cnt_read [7:0] $end
$var reg 1 ^ m_arready $end
$var reg 1 Y m_rlast_stage0 $end
$var reg 1 0" m_rready_stage0 $end
$var reg 2 1" m_rresp_stage0 [1:0] $end
$var reg 1 2" next_state $end
$var reg 1 R o_ren $end
$var reg 1 3" state $end
$upscope $end
$scope module FSM_MASTER_WRITE_inst $end
$var wire 1 * clk $end
$var wire 2 4" m_awburst [1:0] $end
$var wire 8 5" m_awlen [7:0] $end
$var wire 1 = m_awvalid $end
$var wire 1 6" m_wlast $end
$var wire 1 @ m_wvalid $end
$var wire 1 + rst_n $end
$var reg 3 7" b_reps [2:0] $end
$var reg 8 8" cnt_push [7:0] $end
$var reg 1 ] m_awready $end
$var reg 1 V m_wready $end
$var reg 1 9" next_state $end
$var reg 1 L o_wen $end
$var reg 1 M select_address $end
$var reg 1 :" state $end
$upscope $end
$scope module LANE_EN_WRITE_inst $end
$var wire 8 ;" byte_enable [7:0] $end
$var wire 1 * clk $end
$var wire 64 <" i_data [63:0] $end
$var wire 1 + rst_n $end
$var reg 64 =" o_data [63:0] $end
$upscope $end
$scope module RAM_inst $end
$var wire 1 * clk $end
$var wire 64 >" i_data [63:0] $end
$var wire 32 ?" i_read_address [31:0] $end
$var wire 1 R i_ren $end
$var wire 1 L i_wen $end
$var wire 32 @" i_write_address [31:0] $end
$var wire 1 + rst_n $end
$var reg 64 A" o_data [63:0] $end
$var integer 32 B" i [31:0] $end
$upscope $end
$upscope $end
$upscope $end
$enddefinitions $end
#0
$dumpvars
b10000000000 B"
bx A"
b0 @"
b0 ?"
b0 >"
b0 ="
b0 <"
b0 ;"
0:"
09"
b0 8"
b111 7"
06"
b0 5"
b0 4"
03"
02"
b0 1"
00"
b0 /"
b0 ."
b0 -"
b0 ,"
b10000 +"
b0 *"
b0 )"
b0 ("
b0 '"
b10000 &"
b0 %"
b0 $"
b0 #"
b0xxxxxxxxxxxxxxxxxxxxxxxxxxxxxxxxxxxxxxxxxxxxxxxxxxxxxxxxxxxxxxxx00 ""
b10000 !"
b0 ~
b0 }
b0 |
b0 {
b10000 z
b0 y
b0 x
b0 w
b0 v
b10000 u
b0 t
b0 s
b0 r
b0 q
b0 p
b1 o
b0 n
b0 m
b0 l
b1 k
b0 j
b0 i
b0 h
b111 g
b0 f
b0 e
b111 d
1c
1b
1a
0`
0_
0^
0]
0\
b0 [
bx Z
0Y
0X
b0 W
0V
b0 U
b0 T
b0 S
0R
b0 Q
b0 P
b0 O
0N
0M
0L
b0 K
b0 J
b0 I
b0 H
b0 G
b0 F
b0 E
b0 D
b0 C
b0 B
b0 A
0@
1?
1>
0=
0<
0;
b0 :
09
b0 8
07
06
05
b0 4
b0 3
b0 2
b0 1
00
b0 /
b0 .
b0 -
b0 ,
0+
0*
0)
0(
b0 '
1&
b0 %
0$
b0 #
1"
0!
$end
#5
b0 ""
b0 Z
b0 A"
b10000 &"
b10000 u
b10000 !"
b10000 +"
b10000 z
1*
#10
0*
#15
b10000 z
b10000 +"
b10000 !"
b10000 u
b10000 &"
1*
#20
0*
#25
b10000 &"
b10000 u
b10000 !"
b10000 +"
b10000 z
1*
#30
0*
1+
#35
b11 ""
b11 W
b11 ."
b11 1"
1*
#40
0*
b11111111 :
b11111111 J
b10111111111 '"
b101 8
b101 I
1;
b111 3
b111 G
b11 4
b11 H
b10000011101100000000000000000000000000000000 v
b1 2
b1 F
15
#45
1V
19"
1@
1=
0a
0b
b11111111 ;"
b101 <"
b1000 k
b11 j
b111 5"
b1 4"
b1 *"
b10111111111 S
b10111111111 ("
b1 y
b10000011101100000000000000000000000000000000 T
b10000011101100000000000000000000000000000000 w
1*
#50
0*
b11011111111 '"
b110 8
b110 I
05
#55
b110 <"
1M
1V
b11011111111 S
b11011111111 ("
b1 )"
b10 *"
1:"
b1 8"
1L
b101 K
b101 ="
b101 >"
1*
#60
0*
b11111111111 '"
b111 8
b111 I
#65
b111 <"
b110 K
b110 ="
b110 >"
b1000 e
b1000 l
b1000 @"
b10 8"
b11111111111 S
b11111111111 ("
b10 )"
b11 *"
1*
#70
0*
b100011111111 '"
b1000 8
b1000 I
#75
b1000 <"
b100011111111 S
b100011111111 ("
b11 )"
b100 *"
b11 8"
b10000 e
b10000 l
b10000 @"
b111 K
b111 ="
b111 >"
1*
#80
0*
b100111111111 '"
b1001 8
b1001 I
#85
b1001 <"
b1000 K
b1000 ="
b1000 >"
b11000 e
b11000 l
b11000 @"
b100 8"
b100111111111 S
b100111111111 ("
b100 )"
b101 *"
1*
#90
0*
b101011111111 '"
b1010 8
b1010 I
#95
b1010 <"
b101011111111 S
b101011111111 ("
b101 )"
b110 *"
b101 8"
b100000 e
b100000 l
b100000 @"
b1001 K
b1001 ="
b1001 >"
1*
